nabil/__init__.py
nabil/ip_base.py
nabil/some_basic_op.py
nabil-0.0.4.dist-info/LICENCE
nabil-0.0.4.dist-info/METADATA
nabil-0.0.4.dist-info/WHEEL
nabil-0.0.4.dist-info/top_level.txt
nabil-0.0.4.dist-info/RECORD
