Metadata-Version: 2.1
Name: nabil
Version: 0.0.4
Summary: My Pypi Module
Home-page: UNKNOWN
Author: Nabil Rahman
Author-email: rjnabilrahman@gmail.com
License: UNKNOWN
Keywords: nabil,nabil-official,easy syntax,python project
Platform: UNKNOWN
Classifier: Development Status :: 1 - Planning
Classifier: Intended Audience :: Developers
Classifier: Programming Language :: Python :: 3
Classifier: Operating System :: Unix
Classifier: Operating System :: MacOS :: MacOS X
Classifier: Operating System :: Microsoft :: Windows
License-File: LICENCE
Requires-Dist: requests
Requires-Dist: BeautifulSoup4
